discord/ext/games/__init__.py
discord/ext/games/tic_tac_toe/__init__.py
discord/ext/games/tic_tac_toe/config.py
discord/ext/games/tic_tac_toe/core.py
discord_ext_games-1.1.6.dist-info/METADATA
discord_ext_games-1.1.6.dist-info/WHEEL
discord_ext_games-1.1.6.dist-info/top_level.txt
discord_ext_games-1.1.6.dist-info/RECORD
