Metadata-Version: 2.1
Name: discord-ext-games
Version: 1.1.6
Summary: This library provides bunch of games that can be played on discord.
Home-page: https://github.com/Wiper-R/discord-ext-games
Author: Wiper-R
License: MIT
Platform: UNKNOWN
Requires-Python: >=3.6.0
Requires-Dist: discord.py (>=1.6.1)
